FRsutils/__init__.py
FRsutils/core/__init__.py
FRsutils/core/approximations.py
FRsutils/core/fuzzy_quantifiers.py
FRsutils/core/implicators.py
FRsutils/core/owa_weights.py
FRsutils/core/similarities.py
FRsutils/core/tnorms.py
FRsutils/core/models/__init__.py
FRsutils/core/models/itfrs.py
FRsutils/core/models/owafrs.py
FRsutils/core/models/vqrs.py
FRsutils/utils/__init__.py
FRsutils/utils/plot_fuzzy_quantifiers.py
FRsutils/utils/plot_implicators.py
FRsutils/utils/plot_tnorms.py
FRsutils/utils/snippet.py
frsutils-0.0.3.dist-info/licenses/LICENSE
tests/__init__.py
tests/run_tests_debug_mode.py
tests/snippets.py
tests/syntetic_data_for_tests.py
tests/test_implicators.py
tests/test_itfrs.py
tests/test_owafrs.py
tests/test_similarities.py
tests/test_tnorms.py
frsutils-0.0.3.dist-info/METADATA
frsutils-0.0.3.dist-info/WHEEL
frsutils-0.0.3.dist-info/top_level.txt
frsutils-0.0.3.dist-info/RECORD
