Metadata-Version: 2.4
Name: FRsutils
Version: 0.0.3
Summary: A Python library for fuzzy-rough set utility functions.
Home-page: https://github.com/mehi64/FRsutils
Author: Mehran Amiri
Author-email: Mehran Amiri <meam64@gmail.com>
License:  AGPL-3.0
Project-URL: Homepage, https://github.com/mehi64/FRsutils
Project-URL: Documentation, https://mehi64.github.io/FRsutils/
Keywords: fuzzy-rough sets,mathematics,data science
License-File: LICENSE
Requires-Dist: numpy>=1.21.0
Dynamic: author
Dynamic: home-page
Dynamic: license-file
